.gitignore
.travis.yml
CHANGES.txt
README.rst
setup.cfg
setup.py
pyramid_layer/__init__.py
pyramid_layer/layer.py
pyramid_layer/layout.py
pyramid_layer/renderer.py
pyramid_layer/script.py
pyramid_layer.egg-info/PKG-INFO
pyramid_layer.egg-info/SOURCES.txt
pyramid_layer.egg-info/dependency_links.txt
pyramid_layer.egg-info/entry_points.txt
pyramid_layer.egg-info/not-zip-safe
pyramid_layer.egg-info/requires.txt
pyramid_layer.egg-info/top_level.txt
pyramid_layer/tests/base.py
pyramid_layer/tests/test-layout-html.pt
pyramid_layer/tests/test-layout.pt
pyramid_layer/tests/test_custom.py
pyramid_layer/tests/test_layer.py
pyramid_layer/tests/test_layout.py
pyramid_layer/tests/test_order.py
pyramid_layer/tests/test_renderer.py
pyramid_layer/tests/test_script.py
pyramid_layer/tests/bundle/dir1/view.pt
pyramid_layer/tests/dir1/actions.pt
pyramid_layer/tests/dir1/view.pt